AUTHORS
LICENSE
MANIFEST.in
README
pyforrst.py
setup.py
pyforrst.egg-info/PKG-INFO
pyforrst.egg-info/SOURCES.txt
pyforrst.egg-info/dependency_links.txt
pyforrst.egg-info/not-zip-safe
pyforrst.egg-info/requires.txt
pyforrst.egg-info/top_level.txt
tests/__init__.py
tests/__init__.pyc
tests/test.py
tests/test.pyc