Metadata-Version: 1.0
Name: pyforrst
Version: 0.2
Summary: Python interface to Forrst API
Home-page: http://github.com/paparent/pyforrst
Author: PA Parent
Author-email: paparent@paparent.me
License: MIT
Platform: UNKNOWN
Classifier: Development Status :: 3 - Alpha
Classifier: Programming Language :: Python
Classifier: Intended Audience :: Developers
Classifier: Topic :: Software Development :: Libraries :: Python Modules
Classifier: License :: OSI Approved :: MIT License
